{
  "properties": {
    "activities": [
      {
        "type": "RefreshDataflow",
        "typeProperties": {
          "dataflowId": "e9e127d0-0f6e-a4b4-41af-bb7a99309e31",
          "workspaceId": "00000000-0000-0000-0000-000000000000",
          "notifyOption": "NoNotification",
          "dataflowType": "DataflowFabric"
        },
        "policy": {
          "timeout": "0.12:00:00",
          "retry": 1,
          "retryIntervalInSeconds": 300,
          "secureInput": false,
          "secureOutput": false
        },
        "name": "df_clean_cost_revenue",
        "dependsOn": []
      }
    ]
  }
}